pv_ivcurve/__init__.py
pv_ivcurve/config.py
pv_ivcurve/iv_curve_utils.py
pv_ivcurve/iv_degradation.py
pv_ivcurve/iv_model.py
pv_ivcurve-1.0.dist-info/METADATA
pv_ivcurve-1.0.dist-info/WHEEL
pv_ivcurve-1.0.dist-info/top_level.txt
pv_ivcurve-1.0.dist-info/RECORD
