Metadata-Version: 2.2
Name: pv_ivcurve
Version: 1.0
Summary: IV-curve package
Home-page: https://github.com/AlexandreHugoMathieu/pv_ivcurve
Author: Alexandre MATHIEU
Author-email: mathalex@gmail.com
Requires-Python: >=3.9
Dynamic: author
Dynamic: author-email
Dynamic: description
Dynamic: description-content-type
Dynamic: home-page
Dynamic: requires-python
Dynamic: summary
